rag_chunk-0.4.0.dist-info/licenses/LICENSE
src/__init__.py
src/chunker.py
src/cli.py
src/parser.py
src/scorer.py
rag_chunk-0.4.0.dist-info/METADATA
rag_chunk-0.4.0.dist-info/WHEEL
rag_chunk-0.4.0.dist-info/entry_points.txt
rag_chunk-0.4.0.dist-info/top_level.txt
rag_chunk-0.4.0.dist-info/RECORD
