Metadata-Version: 2.4
Name: rag-chunk
Version: 0.4.0
Summary: CLI tool to parse, chunk, and evaluate Markdown documents for RAG pipelines with token-accurate chunking support
Author: messkan
License: MIT
Keywords: rag,chunking,markdown,retrieval
Classifier: Programming Language :: Python :: 3
Classifier: License :: OSI Approved :: MIT License
Classifier: Topic :: Software Development :: Libraries :: Python Modules
Classifier: Intended Audience :: Developers
Requires-Python: >=3.9
License-File: LICENSE
Provides-Extra: rich
Requires-Dist: rich>=12.0.0; extra == "rich"
Provides-Extra: tiktoken
Requires-Dist: tiktoken>=0.5.0; extra == "tiktoken"
Provides-Extra: langchain
Requires-Dist: langchain>=0.1.0; extra == "langchain"
Requires-Dist: langchain-text-splitters>=0.0.1; extra == "langchain"
Provides-Extra: semantic
Requires-Dist: sentence-transformers>=2.2.0; extra == "semantic"
Requires-Dist: numpy>=1.24.0; extra == "semantic"
Provides-Extra: all
Requires-Dist: rich>=12.0.0; extra == "all"
Requires-Dist: tiktoken>=0.5.0; extra == "all"
Requires-Dist: langchain>=0.1.0; extra == "all"
Requires-Dist: langchain-text-splitters>=0.0.1; extra == "all"
Requires-Dist: sentence-transformers>=2.2.0; extra == "all"
Requires-Dist: numpy>=1.24.0; extra == "all"
Dynamic: license-file
